covid19pyclient/__init__.py
covid19pyclient/__main__.py
covid19pyclient/endpoints.py
covid19pyclient/exceptions.py
covid19pyclient/valid_parameters.py
covid19pyclient-1.0.0.dist-info/LICENSE
covid19pyclient-1.0.0.dist-info/METADATA
covid19pyclient-1.0.0.dist-info/WHEEL
covid19pyclient-1.0.0.dist-info/top_level.txt
covid19pyclient-1.0.0.dist-info/RECORD
