Metadata-Version: 2.1
Name: covid19pyclient
Version: 1.0.0
Summary: A Python Wrapper around the COVID-19 API 'https://github.com/marlon360/rki-covid-api'.
Home-page: https://github.com/NiklasTiede/covid19pyclient
Author: Niklas Tiede
Author-email: niklastiede2@gmail.com
License: MIT license
Project-URL: Documentation, https://covid19pyclient.readthedocs.io/en/latest/
Project-URL: Source Code, https://github.com/NiklasTiede/covid19pyclient
Platform: any
Classifier: Development Status :: 4 - Beta
Classifier: Intended Audience :: Developers
Classifier: Intended Audience :: Science/Research
Classifier: License :: OSI Approved :: MIT License
Classifier: Natural Language :: English
Classifier: Programming Language :: Python :: 3
Classifier: Programming Language :: Python :: 3.6
Classifier: Programming Language :: Python :: 3.7
Classifier: Programming Language :: Python :: 3.8
Classifier: Programming Language :: Python :: 3.9
Requires-Python: >=3.6
Requires-Dist: requests (>=2.21.0)
Provides-Extra: dev
Requires-Dist: pytest ; extra == 'dev'
Requires-Dist: pytest-cov ; extra == 'dev'
Requires-Dist: tox ; extra == 'dev'
Requires-Dist: pre-commit ; extra == 'dev'
